setup.py
hawkular_client_cli/__init__.py
hawkular_client_cli/command_line.py
hawkular_client_cli.egg-info/PKG-INFO
hawkular_client_cli.egg-info/SOURCES.txt
hawkular_client_cli.egg-info/dependency_links.txt
hawkular_client_cli.egg-info/entry_points.txt
hawkular_client_cli.egg-info/not-zip-safe
hawkular_client_cli.egg-info/requires.txt
hawkular_client_cli.egg-info/top_level.txt