Metadata-Version: 1.1
Name: hawkular-client-cli
Version: 0.18.2
Summary: Hawkular client cli
Home-page: http://github.com/yaacov/hawkular-client-cli
Author: Yaacov Zamir
Author-email: yzamir@redhat.com
License: Apache License 2.0
Platform: UNKNOWN
Classifier: Development Status :: 4 - Beta
Classifier: Intended Audience :: Developers
Classifier: Programming Language :: Python
Classifier: Programming Language :: Python :: 2
Classifier: Programming Language :: Python :: 3
Classifier: Topic :: System :: Monitoring
